{
  "entries": [
    {
      "id": "weathered_local",
      "category": "archetype",
      "name": "Weathered Local",
      "allowed_roles": ["innkeeper", "watchman", "guard", "guide"],
      "allowed_archetypes": [],
      "allowed_settlement_archetypes": ["waystop", "farm_enclave_village", "village"],
      "allowed_biomes": ["stone_halls", "bone_gallery", "rootvault", "fungal_warrens", "farm_enclave"],
      "allowed_section_kinds": ["settlement"],
      "allowed_shop_types": [],
      "required_shop_roles": [],
      "requires_hazard": false
    },
    {
      "id": "guarded_trader",
      "category": "archetype",
      "name": "Guarded Trader",
      "allowed_roles": ["merchant", "innkeeper", "guide"],
      "allowed_archetypes": [],
      "allowed_settlement_archetypes": ["waystop", "market_den", "village"],
      "allowed_biomes": ["stone_halls", "arcane_halls", "bone_gallery", "waterways"],
      "allowed_section_kinds": ["settlement"],
      "allowed_shop_types": [],
      "required_shop_roles": [],
      "requires_hazard": false
    },
    {
      "id": "route_reader",
      "category": "archetype",
      "name": "Route Reader",
      "allowed_roles": ["guide", "watchman", "merchant"],
      "allowed_archetypes": [],
      "allowed_settlement_archetypes": ["waystop", "beast_tether_hold", "farm_enclave_village"],
      "allowed_biomes": ["waterways", "stone_halls", "rootvault", "garden_hold"],
      "allowed_section_kinds": ["settlement"],
      "allowed_shop_types": [],
      "required_shop_roles": [],
      "requires_hazard": false
    },
    {
      "id": "pressed_caretaker",
      "category": "archetype",
      "name": "Pressed Caretaker",
      "allowed_roles": ["innkeeper", "healer", "watchman", "guard"],
      "allowed_archetypes": [],
      "allowed_settlement_archetypes": ["waystop", "farm_enclave_village", "hidden_refuge", "village"],
      "allowed_biomes": ["farm_enclave", "garden_hold", "bone_gallery", "fungal_warrens"],
      "allowed_section_kinds": ["settlement"],
      "allowed_shop_types": [],
      "required_shop_roles": [],
      "requires_hazard": false
    }
  ]
}
